jhlangtool/FromExcelToJson.py
jhlangtool/FromJsonToExcel.py
jhlangtool/__init__.py
jhlangtool/entrypoint.py
jhlangtool/processArgs.py
jhlangtool/helpMessages/excelToJsonHelp.txt
jhlangtool/helpMessages/generateExcelLongHelp.txt
jhlangtool/helpMessages/generateExcelShortHelp.txt
jhlangtool/helpMessages/toolHelp.txt
jhlangtool-0.8.1.dist-info/DESCRIPTION.rst
jhlangtool-0.8.1.dist-info/METADATA
jhlangtool-0.8.1.dist-info/RECORD
jhlangtool-0.8.1.dist-info/WHEEL
jhlangtool-0.8.1.dist-info/entry_points.txt
jhlangtool-0.8.1.dist-info/metadata.json
jhlangtool-0.8.1.dist-info/top_level.txt
