Metadata-Version: 2.0
Name: jhlangtool
Version: 0.8.1
Summary: Program that converts jhipster language-specific JSON files into an excel file and back
Home-page: https://github.com/MartinVrbovcan/jhlangtool
Author: Martin Vrbovčan
Author-email: UNKNOWN
License: UNKNOWN
Platform: UNKNOWN
Requires-Python: >=3
Requires-Dist: xlsxwriter (>=1.0.3)
Requires-Dist: pandas
